gitea_github_sync/__init__.py
gitea_github_sync/__main__.py
gitea_github_sync/cli.py
gitea_github_sync/config.py
gitea_github_sync/gitea.py
gitea_github_sync/github.py
gitea_github_sync/migration.py
gitea_github_sync/repository.py
gitea_github_sync-0.2.0.dist-info/LICENSE
gitea_github_sync-0.2.0.dist-info/METADATA
gitea_github_sync-0.2.0.dist-info/WHEEL
gitea_github_sync-0.2.0.dist-info/entry_points.txt
gitea_github_sync-0.2.0.dist-info/RECORD
