Metadata-Version: 2.1
Name: gitea-github-sync
Version: 0.2.0
Summary: Syncs your gitea instance with your Github account
Home-page: https://github.com/Muscaw/gitea-github-sync
License: MIT
Author: Kevin Grandjean
Author-email: Muscaw@users.noreply.github.com
Requires-Python: >=3.8.1,<4.0.0
Classifier: Development Status :: 5 - Production/Stable
Classifier: Environment :: Console
Classifier: Intended Audience :: Developers
Classifier: Intended Audience :: End Users/Desktop
Classifier: Intended Audience :: Information Technology
Classifier: Intended Audience :: System Administrators
Classifier: License :: OSI Approved :: MIT License
Classifier: Operating System :: OS Independent
Classifier: Programming Language :: Python :: 3
Classifier: Programming Language :: Python :: 3.9
Classifier: Programming Language :: Python :: 3.10
Classifier: Programming Language :: Python :: 3.11
Classifier: Programming Language :: Python :: 3.12
Classifier: Programming Language :: Python :: 3.8
Classifier: Typing :: Typed
Requires-Dist: click (>=8.1.3,<9.0.0)
Requires-Dist: piny (>=0.6,<1.1)
Requires-Dist: pydantic (>=1.10.4,<3.0.0)
Requires-Dist: pygithub (>=1.57,<2.0)
Requires-Dist: requests (>=2.28.1,<3.0.0)
Requires-Dist: rich (>=13.0.0,<14.0.0)
